OpenSync/__init__.py
OpenSync/i_o.py
OpenSync/markers.py
OpenSync/sensors.py
OpenSync/GazepointLSL/LSLGazepoint.py
OpenSync/GazepointLSL/LSLGazepointBiometrics.py
OpenSync/GazepointLSL/__pycache__/LSLGazepoint.cpython-36.pyc
OpenSync/GazepointLSL/__pycache__/LSLGazepointBiometrics.cpython-36.pyc
OpenSync/KinectBodyBasicsLSL/BodyBasics.res
OpenSync/KinectBodyBasicsLSL/BodyBasicsLSL.exe
OpenSync/KinectBodyBasicsLSL/BodyBasicsLSL.ilk
OpenSync/KinectBodyBasicsLSL/BodyBasicsLSL.log
OpenSync/KinectBodyBasicsLSL/BodyBasicsLSL.pdb
OpenSync/KinectBodyBasicsLSL/BodyBasicsLSL.vcxproj.FileListAbsolute.txt
OpenSync/KinectBodyBasicsLSL/Kinect20.Face.lib
OpenSync/KinectBodyBasicsLSL/Kinect20.Fusion.lib
OpenSync/KinectBodyBasicsLSL/Kinect20.VisualGestureBuilder.lib
OpenSync/KinectBodyBasicsLSL/Kinect20.dll
OpenSync/KinectBodyBasicsLSL/Kinect20.lib
OpenSync/KinectBodyBasicsLSL/lsl.dll
OpenSync/KinectBodyBasicsLSL/lsl.exp
OpenSync/KinectBodyBasicsLSL/lsl.ilk
OpenSync/KinectBodyBasicsLSL/lsl.lib
OpenSync/KinectBodyBasicsLSL/lsl.pdb
OpenSync/KinectBodyBasicsLSL/main.obj
OpenSync/KinectBodyBasicsLSL/vc142.idb
OpenSync/KinectBodyBasicsLSL/vc142.pdb
OpenSync/KinectBodyBasicsLSL/BodyBasicsLSL.tlog/BodyBasicsLSL.lastbuildstate
OpenSync/KinectBodyBasicsLSL/BodyBasicsLSL.tlog/CL.command.1.tlog
OpenSync/KinectBodyBasicsLSL/BodyBasicsLSL.tlog/CL.read.1.tlog
OpenSync/KinectBodyBasicsLSL/BodyBasicsLSL.tlog/CL.write.1.tlog
OpenSync/KinectBodyBasicsLSL/BodyBasicsLSL.tlog/link.command.1.tlog
OpenSync/KinectBodyBasicsLSL/BodyBasicsLSL.tlog/link.read.1.tlog
OpenSync/KinectBodyBasicsLSL/BodyBasicsLSL.tlog/link.write.1.tlog
OpenSync/KinectBodyBasicsLSL/BodyBasicsLSL.tlog/rc.command.1.tlog
OpenSync/KinectBodyBasicsLSL/BodyBasicsLSL.tlog/rc.read.1.tlog
OpenSync/KinectBodyBasicsLSL/BodyBasicsLSL.tlog/rc.write.1.tlog
OpenSync/LabRecorder/LabRecorder.cfg
OpenSync/LabRecorder/LabRecorder.exe
OpenSync/LabRecorder/LabRecorderCLI.exe
OpenSync/LabRecorder/Qt5Core.dll
OpenSync/LabRecorder/Qt5Gui.dll
OpenSync-0.2.2.dist-info/LICENSE.txt
OpenSync-0.2.2.dist-info/METADATA
OpenSync-0.2.2.dist-info/WHEEL
OpenSync-0.2.2.dist-info/top_level.txt
OpenSync-0.2.2.dist-info/RECORD
