Metadata-Version: 2.1
Name: OpenSync
Version: 0.2.2
Summary: A software suite for sensor syncrhonization
Home-page: UNKNOWN
Author: Moein Razavi
Author-email: moeinrazavi@tamu.edu
License: UNKNOWN
Keywords: synchronization
Platform: UNKNOWN
License-File: LICENSE.txt
Requires-Dist: pyOpenBCI
Requires-Dist: mindwavelsl
Requires-Dist: pylsl
Requires-Dist: xmltodict
